setup.py
awsml_distributions/Binomialdistribution.py
awsml_distributions/Gaussiandistribution.py
awsml_distributions/Generaldistribution.py
awsml_distributions/__init__.py
awsml_distributions.egg-info/PKG-INFO
awsml_distributions.egg-info/SOURCES.txt
awsml_distributions.egg-info/dependency_links.txt
awsml_distributions.egg-info/not-zip-safe
awsml_distributions.egg-info/top_level.txt