Metadata-Version: 1.0
Name: awsml-distributions
Version: 0.1
Summary: Gaussian distributions
Home-page: UNKNOWN
Author: Simon Peter Asiimwe
Author-email: smasiimwe@gmail.com
License: UNKNOWN
Platform: UNKNOWN
